attribute_name_validator/ATTRIBUTE_NAMING_GUIDELINES_AND_ANALYSIS_REPORT_USAGE.html
attribute_name_validator/CATALOG.xlsx
attribute_name_validator/__init__.py
attribute_name_validator/__main__.py
attribute_name_validator/analyze.py
attribute_name_validator/catalog.json
attribute_name_validator/config.py
attribute_name_validator/model.py
attribute_name_validator/py.typed
attribute_name_validator/utilities.py
attribute_name_validator-0.0.0.dist-info/METADATA
attribute_name_validator-0.0.0.dist-info/WHEEL
attribute_name_validator-0.0.0.dist-info/entry_points.txt
attribute_name_validator-0.0.0.dist-info/top_level.txt
attribute_name_validator-0.0.0.dist-info/RECORD
