Metadata-Version: 2.1
Name: attribute-name-validator
Version: 0.0.0
Summary: Attribute Name Validator
Home-page: https://github.com/siddartham/attribute-name-validator
Author-email: reddy.siddartha53@gmail.com
Requires-Python: ~=3.8
Requires-Dist: oapi ~=1.62
Requires-Dist: openpyxl ~=3.1
Requires-Dist: dataclasses ~=0.8 ; python_version <= "3.6"
